libname/__init__.py
libname/hello.py
hellopdojfi-0.0.1.dist-info/METADATA
hellopdojfi-0.0.1.dist-info/WHEEL
hellopdojfi-0.0.1.dist-info/top_level.txt
hellopdojfi-0.0.1.dist-info/RECORD
